geolibs/__init__.py
geolibs/engine_cocoext.py
geolibs/engine_cocometric.py
geolibs/engine_csv.py
geolibs/engine_hub.py
geolibs/engine_mask.py
geolibs/enginelogger_hook.py
geolibs/inference.py
geolibs/loading.py
geolibs/misc.py
geolibs/transforms.py
tools/dist_train.sh
tools/model_converters/vit2mmseg.py
tools/test.py
tools/train.py
geolibs-0.0.35.dist-info/METADATA
geolibs-0.0.35.dist-info/WHEEL
geolibs-0.0.35.dist-info/entry_points.txt
geolibs-0.0.35.dist-info/RECORD
