Metadata-Version: 2.1
Name: geolibs
Version: 0.0.35
Summary: A wrapper library that integrates GeoEngine and MMLab libraries for GeoSpatial ML development.
Home-page: https://github.com/granularai/geolibs
License: MIT
Author: Sagar Verma
Author-email: sagar@granular.ai
Requires-Python: >=3.8.0,<4.0.0
Classifier: Intended Audience :: Developers
Classifier: License :: OSI Approved :: MIT License
Classifier: Natural Language :: English
Classifier: Programming Language :: Python :: 3
Classifier: Programming Language :: Python :: 3.8
Classifier: Programming Language :: Python :: 3.9
Classifier: Programming Language :: Python :: 3.10
Classifier: Programming Language :: Python :: 3.11
Classifier: Programming Language :: Python :: 3.12
Requires-Dist: albumentations (==1.3.0)
Requires-Dist: granular-engine (>=0.2.4,<0.3.0)
Requires-Dist: numpy (==1.24.3)
Requires-Dist: prettytable (==3.7.0)
Requires-Dist: rasterio (==1.3.6)
Requires-Dist: shapely (==2.0.1)
Requires-Dist: tqdm (==4.65.0)
Project-URL: Repository, https://github.com/granularai/geolibs
